inventree_supplier_panel/__init__.py
inventree_supplier_panel/digikey.py
inventree_supplier_panel/farnell.py
inventree_supplier_panel/meta_access.py
inventree_supplier_panel/mouser.py
inventree_supplier_panel/request_wrappers.py
inventree_supplier_panel/supplier_panel.py
inventree_supplier_panel/test_supplier_panel.py
inventree_supplier_panel/version.py
inventree_supplier_panel/templates/supplier_panel/add_supplierpart.html
inventree_supplier_panel/templates/supplier_panel/mouser.html
inventree_supplier_panel-0.6.0.dist-info/licenses/LICENSE
inventree_supplier_panel-0.6.0.dist-info/METADATA
inventree_supplier_panel-0.6.0.dist-info/WHEEL
inventree_supplier_panel-0.6.0.dist-info/entry_points.txt
inventree_supplier_panel-0.6.0.dist-info/top_level.txt
inventree_supplier_panel-0.6.0.dist-info/RECORD
