Metadata-Version: 2.4
Name: inventree-supplier-panel
Version: 0.6.0
Summary: Syncronize a PO with a supplier online store
Home-page: https://github.com/SergeoLacruz/inventree-supplier-panel
Author: Michael Buchmann
Author-email: michael@buchmann.ruhr
License: MIT
Keywords: inventree supplier inventory store purchase order
Requires-Python: >=3.6
License-File: LICENSE
Dynamic: author
Dynamic: author-email
Dynamic: description
Dynamic: description-content-type
Dynamic: home-page
Dynamic: keywords
Dynamic: license
Dynamic: license-file
Dynamic: requires-python
Dynamic: summary
